fantasio/GUI_functions.py
fantasio/__init__.py
fantasio/auto.py
fantasio/automatic.py
fantasio/fantasio.py
fantasio/fitting_GUI_functions.py
fantasio/inter.py
fantasio/interactive.py
fantasio-0.1.2.dist-info/licenses/LICENSE
fantasio-0.1.2.dist-info/METADATA
fantasio-0.1.2.dist-info/WHEEL
fantasio-0.1.2.dist-info/entry_points.txt
fantasio-0.1.2.dist-info/top_level.txt
fantasio-0.1.2.dist-info/RECORD
