Metadata-Version: 2.4
Name: fantasio
Version: 0.1.2
Summary: Fantasio, normalization tool for SPIRou .fits file
Author-email: Lisa Drouglazet <lisa.drouglazet@univ-grenoble-alpes.fr>
License-Expression: Apache-2.0
Requires-Python: >=3.6
License-File: LICENSE
Requires-Dist: numpy
Requires-Dist: scipy
Requires-Dist: matplotlib
Requires-Dist: astropy
Requires-Dist: pandas
Dynamic: license-file
